[{ "_id" : { "$oid" : "546e6a143134650002020000" }, "name" : "Nao_celica", "count" : 2, "icon" : "http://pbs.twimg.com/profile_images/526662230058598400/16vwTCFk_normal.jpeg" },{ "_id" : { "$oid" : "546e914f3134650002030000" }, "name" : "kei_an", "count" : 11, "icon" : "http://pbs.twimg.com/profile_images/533646450643582978/dWy5uHtu_normal.jpeg" },{ "_id" : { "$oid" : "546e92cc3134650002040000" }, "name" : "ppoi", "count" : 43, "icon" : "http://pbs.twimg.com/profile_images/1352493511/emblem100_normal.png" },{ "_id" : { "$oid" : "546e96be3134650002050000" }, "name" : "mandarin_7", "count" : 22, "icon" : "http://pbs.twimg.com/profile_images/524827602582638592/4uK9DRd7_normal.jpeg" },{ "_id" : { "$oid" : "546ea15f3134650002060000" }, "name" : "kurenai_ageha", "count" : 8, "icon" : "http://pbs.twimg.com/profile_images/535558862145736705/aramruuf_normal.jpeg" },{ "_id" : { "$oid" : "546eae103134650002070000" }, "name" : "tdtds", "count" : 20, "icon" : "http://pbs.twimg.com/profile_images/459308842824646657/qbBibKKU_normal.jpeg" },{ "_id" : { "$oid" : "546eae343134650002080000" }, "name" : "hdk124", "count" : 1, "icon" : "http://pbs.twimg.com/profile_images/494659114895568897/ZpT7R1L8_normal.jpeg" },{ "_id" : { "$oid" : "546eb0c53134650002090000" }, "name" : "katsuyamaruta", "count" : 1, "icon" : "http://pbs.twimg.com/profile_images/1407709168/maruta_normal.jpg" },{ "_id" : { "$oid" : "546eb48f31346500020a0000" }, "name" : "gizmonchi", "count" : 4, "icon" : "http://pbs.twimg.com/profile_images/2598363900/image_normal.jpg" },{ "_id" : { "$oid" : "546eb6d931346500020b0000" }, "name" : "h12o", "count" : 5, "icon" : "http://pbs.twimg.com/profile_images/494114070354612225/PPseoXS5_normal.jpeg" },{ "_id" : { "$oid" : "546eb8ec31346500020c0000" }, "name" : "pauwaun", "count" : 1, "icon" : "http://pbs.twimg.com/profile_images/458928530688995328/7r_Z7r1P_normal.jpeg" },{ "_id" : { "$oid" : "546ec14e31346500020d0000" }, "name" : "raydive", "count" : 6, "icon" : "http://pbs.twimg.com/profile_images/422560897379217408/YCYvfKqg_normal.jpeg" },{ "_id" : { "$oid" : "546ec1c031346500020e0000" }, "name" : "naritamasahiro", "count" : 98, "icon" : "http://pbs.twimg.com/profile_images/723492641/icon_normal.jpg" },{ "_id" : { "$oid" : "546ec5ff31346500020f0000" }, "name" : "yuutamickey", "count" : 26, "icon" : "http://pbs.twimg.com/profile_images/1810618550/image_normal.jpg" },{ "_id" : { "$oid" : "546ec78e3134650002100000" }, "name" : "snwnoblue", "count" : 1, "icon" : "http://pbs.twimg.com/profile_images/1131617222/momonga_normal.jpg" },{ "_id" : { "$oid" : "546ed1183134650002110000" }, "name" : "ak2next", "count" : 13, "icon" : "http://abs.twimg.com/sticky/default_profile_images/default_profile_2_normal.png" },{ "_id" : { "$oid" : "546ed7803134650002120000" }, "name" : "0511aya", "count" : 9, "icon" : "http://pbs.twimg.com/profile_images/524929556390506496/QqCYGEQM_normal.jpeg" },{ "_id" : { "$oid" : "546eebbb3134650002130000" }, "name" : "appleissoul", "count" : 8, "icon" : "http://pbs.twimg.com/profile_images/514442302769471488/BMXMOTw6_normal.jpeg" },{ "_id" : { "$oid" : "546ef0e03235310002000000" }, "name" : "x2nosk", "count" : 8, "icon" : "http://pbs.twimg.com/profile_images/462094516959199233/K_tI0uPP_normal.jpeg" },{ "_id" : { "$oid" : "546ef3023235310002010000" }, "name" : "rship1500", "count" : 1, "icon" : "http://pbs.twimg.com/profile_images/502419945431392257/g-vkYV6h_normal.jpeg" },{ "_id" : { "$oid" : "546efb233235310002020000" }, "name" : "shion103", "count" : 1, "icon" : "http://pbs.twimg.com/profile_images/1419869474/shion103_normal" },{ "_id" : { "$oid" : "546f00543235310002030000" }, "name" : "DALUMA", "count" : 21, "icon" : "http://pbs.twimg.com/profile_images/511119991672823808/PmdWbBeR_normal.png" },{ "_id" : { "$oid" : "546f09083235310002040000" }, "name" : "yucchan0129", "count" : 15, "icon" : "http://pbs.twimg.com/profile_images/536779117341839361/YCO0ijgC_normal.jpeg" },{ "_id" : { "$oid" : "546f0c663235310002050000" }, "name" : "hide_24", "count" : 10, "icon" : "http://pbs.twimg.com/profile_images/2855457579/b95da36311ed0cf8520929e4d150b9c3_normal.png" },{ "_id" : { "$oid" : "546f0dbb3235310002060000" }, "name" : "maplia", "count" : 1, "icon" : "http://pbs.twimg.com/profile_images/509709119771521024/D-Xsn_8U_normal.png" },{ "_id" : { "$oid" : "546f0dfc3235310002070000" }, "name" : "kayakaya", "count" : 3, "icon" : "http://pbs.twimg.com/profile_images/655431923/avator_trans_normal.png" },{ "_id" : { "$oid" : "546f12143235310002080000" }, "name" : "naribon7", "count" : 21, "icon" : "http://pbs.twimg.com/profile_images/2503052370/image_normal.jpg" },{ "_id" : { "$oid" : "546f12313235310002090000" }, "name" : "tetetep", "count" : 5, "icon" : "http://pbs.twimg.com/profile_images/536172582488137728/6zq4aJ_W_normal.png" },{ "_id" : { "$oid" : "546f1ad532353100020a0000" }, "name" : "yamasa", "count" : 11, "icon" : "http://pbs.twimg.com/profile_images/1611665280/222_normal.png" },{ "_id" : { "$oid" : "546f1b2032353100020b0000" }, "name" : "minesweeper96", "count" : 1, "icon" : "http://pbs.twimg.com/profile_images/378800000466480852/23b78071c45b3c94e77d616a2d0ad39a_normal.jpeg" },{ "_id" : { "$oid" : "546f1d1132353100020c0000" }, "name" : "gbgbgb77", "count" : 1, "icon" : "http://pbs.twimg.com/profile_images/519058302735376384/xKjMTi9A_normal.jpeg" },{ "_id" : { "$oid" : "546f20df32353100020d0000" }, "name" : "pocketp", "count" : 23, "icon" : "http://pbs.twimg.com/profile_images/516960466002657280/FTaQDuon_normal.png" },{ "_id" : { "$oid" : "546f254932353100020e0000" }, "name" : "no6v", "count" : 30, "icon" : "http://pbs.twimg.com/profile_images/1069778748/icon_normal.png" },{ "_id" : { "$oid" : "546f25a332353100020f0000" }, "name" : "wata_d", "count" : 3, "icon" : "http://pbs.twimg.com/profile_images/2309145606/wata_d_normal" },{ "_id" : { "$oid" : "546f30423235310002100000" }, "name" : "WhoDatNationJP", "count" : 6, "icon" : "http://pbs.twimg.com/profile_images/500612355479183361/ctpvvjIP_normal.jpeg" },{ "_id" : { "$oid" : "546f35e63235310002110000" }, "name" : "gussan_xj6", "count" : 7, "icon" : "http://pbs.twimg.com/profile_images/992563465/xj6_2_normal.JPG" },{ "_id" : { "$oid" : "546f397d3235310002120000" }, "name" : "soppeee", "count" : 1, "icon" : "http://pbs.twimg.com/profile_images/1198438707/profile_normal.png" },{ "_id" : { "$oid" : "546f39813235310002130000" }, "name" : "hakuri001", "count" : 3, "icon" : "http://pbs.twimg.com/profile_images/1743281076/20090922162146_normal.jpg" },{ "_id" : { "$oid" : "546f3b413235310002140000" }, "name" : "maki_9744", "count" : 10, "icon" : "http://pbs.twimg.com/profile_images/518039902701637633/QsDjYnE8_normal.jpeg" },{ "_id" : { "$oid" : "546f422f3235310002150000" }, "name" : "barista", "count" : 2, "icon" : "http://pbs.twimg.com/profile_images/1291039689/mypic_normal.jpg" },{ "_id" : { "$oid" : "546f42873235310002160000" }, "name" : "nanai_tanbo", "count" : 5, "icon" : "http://pbs.twimg.com/profile_images/520791168146100224/hmpaxZjW_normal.jpeg" },{ "_id" : { "$oid" : "546f444d3235310002170000" }, "name" : "eban", "count" : 2, "icon" : "http://pbs.twimg.com/profile_images/504653456167026688/HR_8-7P2_normal.png" },{ "_id" : { "$oid" : "546f482d3235310002180000" }, "name" : "harapeko_sinsin", "count" : 6, "icon" : "http://pbs.twimg.com/profile_images/430262684513091584/5vO8ns5b_normal.png" },{ "_id" : { "$oid" : "546f49173235310002190000" }, "name" : "foobar_gracoro", "count" : 50, "icon" : "http://pbs.twimg.com/profile_images/2952003435/41d2daa69befb40cb6ab6bcb87c46058_normal.jpeg" },{ "_id" : { "$oid" : "546f4f5732353100021a0000" }, "name" : "ntee", "count" : 22, "icon" : "http://pbs.twimg.com/profile_images/1110735033/gabu_icon_normal.jpg" },{ "_id" : { "$oid" : "546f50ff32353100021b0000" }, "name" : "SAN_Morishi", "count" : 10, "icon" : "http://pbs.twimg.com/profile_images/451014911485681664/3Be0S92G_normal.png" },{ "_id" : { "$oid" : "546f6b1132353100021c0000" }, "name" : "unak", "count" : 10, "icon" : "http://pbs.twimg.com/profile_images/24309032/prof_normal.jpg" },{ "_id" : { "$oid" : "546fd26632353100021d0000" }, "name" : "pal3", "count" : 4, "icon" : "http://pbs.twimg.com/profile_images/753635521/pal4_normal.png" },{ "_id" : { "$oid" : "546fdfd932353100021e0000" }, "name" : "HaramoriYoshina", "count" : 6, "icon" : "http://pbs.twimg.com/profile_images/538571206517989376/_Y2Ck8xE_normal.jpeg" },{ "_id" : { "$oid" : "5470018e32353100021f0000" }, "name" : "king_nomura", "count" : 4, "icon" : "http://pbs.twimg.com/profile_images/1666767583/faceicon111008_3_normal.jpg" },{ "_id" : { "$oid" : "547013dc3235310002200000" }, "name" : "rltm", "count" : 5, "icon" : "http://pbs.twimg.com/profile_images/378800000718529898/6ac8c39d1e11fcadbb73479e4c54ce46_normal.jpeg" },{ "_id" : { "$oid" : "547014483235310002210000" }, "name" : "kozakana", "count" : 3, "icon" : "http://pbs.twimg.com/profile_images/2354406867/vx59jplf6yyskptxx1jx_normal.jpeg" },{ "_id" : { "$oid" : "547016c83235310002220000" }, "name" : "ishihiro1403", "count" : 1, "icon" : "http://pbs.twimg.com/profile_images/429950891303526400/A9rZ7DRb_normal.png" },{ "_id" : { "$oid" : "5470175e3235310002230000" }, "name" : "gonza503", "count" : 1, "icon" : "http://pbs.twimg.com/profile_images/449877339896160256/N0sarj2e_normal.jpeg" },{ "_id" : { "$oid" : "5470382a3235310002240000" }, "name" : "RainbowWave7", "count" : 3, "icon" : "http://pbs.twimg.com/profile_images/2172079369/im_age_normal.jpeg" },{ "_id" : { "$oid" : "5470483c3235310002250000" }, "name" : "sawamaru", "count" : 4, "icon" : "http://pbs.twimg.com/profile_images/289904053/___normal.jpg" },{ "_id" : { "$oid" : "547049583636630002000000" }, "name" : "ta9boh", "count" : 2, "icon" : "http://pbs.twimg.com/profile_images/378800000035133508/82c700cc25a26741f8e26a4f6882f56a_normal.jpeg" },{ "_id" : { "$oid" : "54704dbb3636630002010000" }, "name" : "rin_ne", "count" : 2, "icon" : "http://pbs.twimg.com/profile_images/2833252019/4fa3bc1bd378a22b4c4dc66fa0f5942f_normal.png" },{ "_id" : { "$oid" : "54705a513636630002020000" }, "name" : "xyzelixir", "count" : 5, "icon" : "http://pbs.twimg.com/profile_images/1004265785/Twitter_______normal.jpg" },{ "_id" : { "$oid" : "547065713636630002030000" }, "name" : "takeeasy4696", "count" : 4, "icon" : "http://pbs.twimg.com/profile_images/528462800411062272/x7O87zbm_normal.jpeg" },{ "_id" : { "$oid" : "54706ce23636630002040000" }, "name" : "koyui", "count" : 13, "icon" : "http://pbs.twimg.com/profile_images/439027540686934016/qe3UkNaX_normal.jpeg" },{ "_id" : { "$oid" : "547079e83636630002050000" }, "name" : "muryoimpl", "count" : 3, "icon" : "http://pbs.twimg.com/profile_images/511827500121333760/IRcvBunz_normal.jpeg" },{ "_id" : { "$oid" : "547080833636630002060000" }, "name" : "minimum2scp", "count" : 9, "icon" : "http://pbs.twimg.com/profile_images/1109182861/bobu-middle_normal.jpg" },{ "_id" : { "$oid" : "547092033636630002070000" }, "name" : "Tani_gawa", "count" : 9, "icon" : "http://pbs.twimg.com/profile_images/1193902687/kon_normal.JPG" },{ "_id" : { "$oid" : "5470a9703636630002080000" }, "name" : "main02_crew", "count" : 1, "icon" : "http://pbs.twimg.com/profile_images/530348735142719489/GPdyl86d_normal.jpeg" },{ "_id" : { "$oid" : "54714dd83636630002090000" }, "name" : "yz_y__r", "count" : 1, "icon" : "http://pbs.twimg.com/profile_images/469809441320103936/pRpKRAMm_normal.jpeg" },{ "_id" : { "$oid" : "5471524436366300020a0000" }, "name" : "seitsui", "count" : 1, "icon" : "http://pbs.twimg.com/profile_images/611807606/PA300960_normal.jpg" },{ "_id" : { "$oid" : "5471542636366300020b0000" }, "name" : "mongrelP", "count" : 5, "icon" : "http://pbs.twimg.com/profile_images/3246995796/1d4635ae9a114ae475858f627f8a5168_normal.png" },{ "_id" : { "$oid" : "5471792236366300020c0000" }, "name" : "shin0O", "count" : 10, "icon" : "http://pbs.twimg.com/profile_images/525249418270748673/0_aHoHYE_normal.png" },{ "_id" : { "$oid" : "5471bf276663630002000000" }, "name" : "seiren1999", "count" : 3, "icon" : "http://pbs.twimg.com/profile_images/378800000672193439/8bf8851986273e7e58fe7131d4586e0f_normal.jpeg" },{ "_id" : { "$oid" : "5471c3ec6663630002010000" }, "name" : "kosigayan", "count" : 1, "icon" : "http://abs.twimg.com/sticky/default_profile_images/default_profile_3_normal.png" },{ "_id" : { "$oid" : "5471d8036663630002020000" }, "name" : "bantyo1011", "count" : 3, "icon" : "http://pbs.twimg.com/profile_images/1444626881/bbimage_normal.jpg" },{ "_id" : { "$oid" : "5471e8f46663630002030000" }, "name" : "nossan630", "count" : 1, "icon" : "http://pbs.twimg.com/profile_images/528210285983563776/jskdINI2_normal.jpeg" },{ "_id" : { "$oid" : "5472d3776663630002040000" }, "name" : "HPH", "count" : 4, "icon" : "http://pbs.twimg.com/profile_images/512818107304255489/B4E6L7_F_normal.jpeg" },{ "_id" : { "$oid" : "5472d5d66663630002050000" }, "name" : "yunyun_1106", "count" : 1, "icon" : "http://pbs.twimg.com/profile_images/536164632302325760/Hspaw0Ir_normal.jpeg" },{ "_id" : { "$oid" : "5472e02f6663630002060000" }, "name" : "_______404", "count" : 2, "icon" : "http://pbs.twimg.com/profile_images/534348343493660672/dnJc9lDg_normal.jpeg" },{ "_id" : { "$oid" : "54731fed6264300002000000" }, "name" : "pinokiwo_t", "count" : 4, "icon" : "http://pbs.twimg.com/profile_images/467103129972924416/YIc1NBYy_normal.jpeg" },{ "_id" : { "$oid" : "547321216264300002010000" }, "name" : "freedomcat", "count" : 1, "icon" : "http://pbs.twimg.com/profile_images/532526547949735936/ti77srAD_normal.png" },{ "_id" : { "$oid" : "547324616264300002020000" }, "name" : "faafood", "count" : 1, "icon" : "http://pbs.twimg.com/profile_images/534286599194808321/bWHm0SkH_normal.jpeg" },{ "_id" : { "$oid" : "54733a656264300002030000" }, "name" : "youho0620", "count" : 1, "icon" : "http://pbs.twimg.com/profile_images/536791691269652482/I1yHsFOl_normal.jpeg" },{ "_id" : { "$oid" : "547428366264300002040000" }, "name" : "nari3", "count" : 4, "icon" : "http://pbs.twimg.com/profile_images/438605743919357952/J3xnl33y_normal.png" },{ "_id" : { "$oid" : "54743f586264300002050000" }, "name" : "AngoNakai", "count" : 1, "icon" : "http://pbs.twimg.com/profile_images/2150665221/_____2_normal.jpg" },{ "_id" : { "$oid" : "547444026264300002060000" }, "name" : "kazmasa5150", "count" : 2, "icon" : "http://pbs.twimg.com/profile_images/129867455/20090409021413_normal.png" },{ "_id" : { "$oid" : "54744b466264300002070000" }, "name" : "rehoslmeiro", "count" : 1, "icon" : "http://pbs.twimg.com/profile_images/536722904658878464/K0zWQhWF_normal.jpeg" },{ "_id" : { "$oid" : "547464a46264300002080000" }, "name" : "Echos", "count" : 4, "icon" : "http://pbs.twimg.com/profile_images/424102343345324032/Y8gdgt-0_normal.png" },{ "_id" : { "$oid" : "54749e9d6461370002000000" }, "name" : "taigo", "count" : 4, "icon" : "http://pbs.twimg.com/profile_images/506816058771005440/2oz6cgxq_normal.jpeg" },{ "_id" : { "$oid" : "5474ae2d6461370002010000" }, "name" : "DNBN_27", "count" : 1, "icon" : "http://pbs.twimg.com/profile_images/536934773134864384/BMLV4hxt_normal.jpeg" },{ "_id" : { "$oid" : "5475510d6461370002020000" }, "name" : "yeosrauk_az", "count" : 5, "icon" : "http://pbs.twimg.com/profile_images/528659413934944257/Ogx4Xw4N_normal.jpeg" },{ "_id" : { "$oid" : "54755beb6461370002030000" }, "name" : "cclemooooon", "count" : 1, "icon" : "http://pbs.twimg.com/profile_images/1243719927/F1000029_normal.JPG" },{ "_id" : { "$oid" : "54756fa06461370002040000" }, "name" : "atlntjaj", "count" : 2, "icon" : "http://pbs.twimg.com/profile_images/532114371581734912/6P2UKEUT_normal.jpeg" },{ "_id" : { "$oid" : "547570ea6461370002050000" }, "name" : "mmaipou", "count" : 1, "icon" : "http://pbs.twimg.com/profile_images/532138140891242496/c4kcRqqM_normal.png" },{ "_id" : { "$oid" : "5475a9136461370002060000" }, "name" : "maenonono", "count" : 6, "icon" : "http://pbs.twimg.com/profile_images/521295357771132929/Wk9gP24C_normal.png" },{ "_id" : { "$oid" : "5475b9fe6461370002070000" }, "name" : "amab", "count" : 3, "icon" : "http://pbs.twimg.com/profile_images/378800000421225239/b8fae4f41ba099ab12cb36109c955e0f_normal.jpeg" },{ "_id" : { "$oid" : "5475ba306461370002080000" }, "name" : "dj_cochame", "count" : 1, "icon" : "http://pbs.twimg.com/profile_images/531141489233891328/kbA0hXQv_normal.jpeg" },{ "_id" : { "$oid" : "5476b6583337320002000000" }, "name" : "mfjt", "count" : 2, "icon" : "http://pbs.twimg.com/profile_images/485331566638292992/vcQBhi1g_normal.jpeg" },{ "_id" : { "$oid" : "5476ea563337320002010000" }, "name" : "ikedaikeikedesu", "count" : 2, "icon" : "http://pbs.twimg.com/profile_images/537896419223285760/s3rEB2v3_normal.jpeg" },{ "_id" : { "$oid" : "5476ed9c3337320002020000" }, "name" : "MarimoSkm", "count" : 2, "icon" : "http://pbs.twimg.com/profile_images/468321974112886784/H2gjB05C_normal.jpeg" },{ "_id" : { "$oid" : "5477a67f6661660002000000" }, "name" : "yuuuya58", "count" : 1, "icon" : "http://pbs.twimg.com/profile_images/1512198035/2W4FSd4h_normal" },{ "_id" : { "$oid" : "5477ed8b6661660002010000" }, "name" : "mametomusic", "count" : 3, "icon" : "http://pbs.twimg.com/profile_images/2328488549/2012040910020000_normal.jpg" },{ "_id" : { "$oid" : "5477eea46661660002020000" }, "name" : "hs9587", "count" : 1, "icon" : "http://pbs.twimg.com/profile_images/586821832/chiyochichi_normal.jpg" },{ "_id" : { "$oid" : "547890d06463610002000000" }, "name" : "mibukan", "count" : 1, "icon" : "http://pbs.twimg.com/profile_images/3156568311/94b5844a280dc89f56ae7e19ff7fb426_normal.jpeg" },{ "_id" : { "$oid" : "547898976463610002010000" }, "name" : "fuyuduki", "count" : 1, "icon" : "http://pbs.twimg.com/profile_images/3170744843/0c0bd1205c63898b4dcb9b88357e0af3_normal.jpeg" },{ "_id" : { "$oid" : "547996046463610002020000" }, "name" : "mnakayam23", "count" : 1, "icon" : "http://pbs.twimg.com/profile_images/467603579377709056/BghPXPs4_normal.jpeg" },{ "_id" : { "$oid" : "5479b4eb6463610002030000" }, "name" : "Sinon", "count" : 2, "icon" : "http://pbs.twimg.com/profile_images/450962511546691584/47e4xLfy_normal.jpeg" },{ "_id" : { "$oid" : "547a659e3935630002000000" }, "name" : "komatthi", "count" : 1, "icon" : "http://pbs.twimg.com/profile_images/1197867120/157511_831915817_4373163_n_normal.jpg" },{ "_id" : { "$oid" : "547a68bd3935630002010000" }, "name" : "hnm72", "count" : 1, "icon" : "http://pbs.twimg.com/profile_images/1241215366/0_normal.JPG" },{ "_id" : { "$oid" : "547a7d723935630002020000" }, "name" : "daita", "count" : 2, "icon" : "http://pbs.twimg.com/profile_images/16091572/me_normal.jpg" },{ "_id" : { "$oid" : "547a92383935630002030000" }, "name" : "y_yagi", "count" : 3, "icon" : "http://pbs.twimg.com/profile_images/498752095231541251/V1OhF3N__normal.jpeg" },{ "_id" : { "$oid" : "547bdeb83030330002000000" }, "name" : "EeeSMO", "count" : 1, "icon" : "http://pbs.twimg.com/profile_images/1680988410/dfLSbC9L_normal" },{ "_id" : { "$oid" : "547c5c903030330002010000" }, "name" : "manaty_3m", "count" : 30, "icon" : "http://pbs.twimg.com/profile_images/539396945354039296/BZgt-sDt_normal.jpeg" },{ "_id" : { "$oid" : "547d2fd56362310002000000" }, "name" : "y_aki", "count" : 3, "icon" : "http://pbs.twimg.com/profile_images/539606406370840576/aDxeq_t1_normal.jpeg" },{ "_id" : { "$oid" : "547d40e06362310002010000" }, "name" : "n0kada", "count" : 1, "icon" : "http://pbs.twimg.com/profile_images/428508397948784640/e7ognjNm_normal.jpeg" },{ "_id" : { "$oid" : "5481591e3636660002000000" }, "name" : "sabazo_rz", "count" : 1, "icon" : "http://pbs.twimg.com/profile_images/458968605170741249/GTSiCrXQ_normal.jpeg" },{ "_id" : { "$oid" : "5483e5626235620002000000" }, "name" : "shinchang", "count" : 1, "icon" : "http://pbs.twimg.com/profile_images/538426613/000___normal.jpg" },{ "_id" : { "$oid" : "5484574d6432380002000000" }, "name" : "okiyu", "count" : 1, "icon" : "http://pbs.twimg.com/profile_images/413060023/1388685_3626265432_normal.jpg" },{ "_id" : { "$oid" : "548458876432380002010000" }, "name" : "yukki7291", "count" : 1, "icon" : "http://pbs.twimg.com/profile_images/2818081153/67c39c46baf7ee79116a9fb35e430681_normal.png" },{ "_id" : { "$oid" : "548530b16432380002020000" }, "name" : "marikowatanabe", "count" : 2, "icon" : "http://pbs.twimg.com/profile_images/1311534094/image_normal.jpg" },{ "_id" : { "$oid" : "5485bf726636360002000000" }, "name" : "long_voyager", "count" : 1, "icon" : "http://pbs.twimg.com/profile_images/541625680056688640/t-Gkw5fQ_normal.png" },{ "_id" : { "$oid" : "548670726636360002010000" }, "name" : "jan_go2_jp", "count" : 4, "icon" : "http://pbs.twimg.com/profile_images/1272303638/RIMG0637_R_normal.JPG" },{ "_id" : { "$oid" : "548902e93963300002000000" }, "name" : "khazad_lefty", "count" : 1, "icon" : "http://pbs.twimg.com/profile_images/26751162/Lefty_normal.jpg" },{ "_id" : { "$oid" : "548916c13963300002010000" }, "name" : "hesogerion", "count" : 1, "icon" : "http://pbs.twimg.com/profile_images/527614994167246848/cZoUk0Rv_normal.jpeg" },{ "_id" : { "$oid" : "54891eeb3963300002020000" }, "name" : "Amethyst_Fe", "count" : 1, "icon" : "http://pbs.twimg.com/profile_images/450292868892991489/Ny364Fs4_normal.jpeg" },{ "_id" : { "$oid" : "54894e763963300002030000" }, "name" : "shachi", "count" : 1, "icon" : "http://pbs.twimg.com/profile_images/537018910160089088/UEMkPnpY_normal.png" },{ "_id" : { "$oid" : "5489c0083734640002000000" }, "name" : "wap301", "count" : 1, "icon" : "http://pbs.twimg.com/profile_images/532422277854277632/_6yiO8tP_normal.jpeg" },{ "_id" : { "$oid" : "5489fb813734640002010000" }, "name" : "ivy___ivy", "count" : 1, "icon" : "http://pbs.twimg.com/profile_images/944300114/F1030016_normal.jpg" },{ "_id" : { "$oid" : "548b04c43636350002000000" }, "name" : "lolipopsakura", "count" : 1, "icon" : "http://pbs.twimg.com/profile_images/514443714047905792/Dqbk71ta_normal.jpeg" },{ "_id" : { "$oid" : "548d240e3037330002000000" }, "name" : "kasumisancha", "count" : 1, "icon" : "http://pbs.twimg.com/profile_images/2867415267/ecf9f04101cc168862f3a5f63b408318_normal.jpeg" },{ "_id" : { "$oid" : "548e42c56531370002000000" }, "name" : "ZuMi38", "count" : 1, "icon" : "http://pbs.twimg.com/profile_images/531086614856859648/44RHjhR0_normal.jpeg" },{ "_id" : { "$oid" : "548e43fb6531370002010000" }, "name" : "skull_38jp", "count" : 1, "icon" : "http://pbs.twimg.com/profile_images/524813713526640641/pugpe_g2_normal.png" },{ "_id" : { "$oid" : "548e4c2e6531370002020000" }, "name" : "youonno1star", "count" : 1, "icon" : "http://abs.twimg.com/sticky/default_profile_images/default_profile_4_normal.png" },{ "_id" : { "$oid" : "548e5b5c6531370002030000" }, "name" : "kuzigen", "count" : 1, "icon" : "http://pbs.twimg.com/profile_images/530665276639956992/Uan4j0TD_normal.jpeg" },{ "_id" : { "$oid" : "548e5ba66531370002040000" }, "name" : "YUhideoKI", "count" : 1, "icon" : "http://pbs.twimg.com/profile_images/519851183771365377/hjafRZbn_normal.jpeg" },{ "_id" : { "$oid" : "548f7d623766340002000000" }, "name" : "Uittie53", "count" : 2, "icon" : "http://abs.twimg.com/sticky/default_profile_images/default_profile_1_normal.png" },{ "_id" : { "$oid" : "548f933e3766340002010000" }, "name" : "hirochanchachan", "count" : 1, "icon" : "http://pbs.twimg.com/profile_images/524083353859784704/-Ratqo1k_normal.jpeg" },{ "_id" : { "$oid" : "548ffc4c3766340002020000" }, "name" : "taraokun1023", "count" : 1, "icon" : "http://pbs.twimg.com/profile_images/542165416823369728/Sn-Uw9DI_normal.jpeg" },{ "_id" : { "$oid" : "5490f9433932300002000000" }, "name" : "ich_nmmm", "count" : 6, "icon" : "http://pbs.twimg.com/profile_images/537610681676070912/GI5wtLtn_normal.jpeg" }]
